sparsestack/StackedSparseArray.py
sparsestack/__init__.py
sparsestack/__version__.py
sparsestack/utils.py
sparsestack-0.7.0.dist-info/LICENSE
sparsestack-0.7.0.dist-info/METADATA
sparsestack-0.7.0.dist-info/WHEEL
sparsestack-0.7.0.dist-info/RECORD
