Metadata-Version: 2.3
Name: sparsestack
Version: 0.7.0
Summary: Python library to handle stacks of sparse COO arrays efficiently.
License: MIT
Author: Florian Huber
Author-email: florian.huber@hs-duesseldorf.de
Requires-Python: >=3.10,<3.14
Classifier: License :: OSI Approved :: MIT License
Classifier: Programming Language :: Python :: 3
Classifier: Programming Language :: Python :: 3.10
Classifier: Programming Language :: Python :: 3.11
Classifier: Programming Language :: Python :: 3.12
Classifier: Programming Language :: Python :: 3.13
Requires-Dist: numba (>=0.61.0,<0.62.0)
Requires-Dist: numpy (>=2.1.0)
Requires-Dist: scipy (>=1.15.0,<2.0.0)
